yxmath/__init__.py
yxmath/interval.py
yxmath/lcs.py
yxmath/math.py
yxmath/net.py
yxmath/opt.py
yxmath/set.py
yxmath/split.py
yxmath/stats.py
yxmath/versions.py
yxmath/plot/VennDiagram.py
yxmath/plot/__init__.py
yxmath/plot/histogram.py
yxmath-0.0.7.dist-info/LICENSE
yxmath-0.0.7.dist-info/METADATA
yxmath-0.0.7.dist-info/WHEEL
yxmath-0.0.7.dist-info/top_level.txt
yxmath-0.0.7.dist-info/RECORD
